setup.py
redis_wrap/__init__.py
redis_wrap/redis_bitset.py
redis_wrap/redis_hash.py
redis_wrap/redis_list.py
redis_wrap/redis_set.py
redis_wrap/redis_systems.py
redis_wrap.egg-info/PKG-INFO
redis_wrap.egg-info/SOURCES.txt
redis_wrap.egg-info/dependency_links.txt
redis_wrap.egg-info/top_level.txt
test/test.py