Metadata-Version: 1.1
Name: redis-wrap
Version: 1.4.4
Summary: Implements a wrapper for Redis datatypes so they mimic the datatypes found in Python.
Home-page: http://www.amix.dk/
Author: amix
Author-email: amix@amix.dk
License: BSD
Keywords: redis wrapper
Platform: Any
Classifier: Development Status :: 5 - Production/Stable
Classifier: Intended Audience :: Developers
Classifier: License :: OSI Approved :: BSD License
Classifier: Operating System :: OS Independent
Classifier: Programming Language :: Python
Classifier: Topic :: Software Development :: Libraries :: Python Modules
